closelink_mcp/__init__.py
closelink_mcp/__main__.py
closelink_mcp/resources/cl-openapi.json
closelink_mcp-1.1.7.dist-info/WHEEL
closelink_mcp-1.1.7.dist-info/entry_points.txt
closelink_mcp-1.1.7.dist-info/METADATA
closelink_mcp-1.1.7.dist-info/RECORD
