Metadata-Version: 2.3
Name: closelink-mcp
Version: 1.1.7
Summary: Closelink MCP Server
Requires-Dist: fastmcp==2.3.1
Requires-Dist: python-dotenv>=1.1.0
Requires-Python: >=3.13
